__init__.py
mds_remote.py
mds_ssh_machine.py
mdsconnector.py
setup.py
tryit/bin/activate_this.py
mdsconnector-1.8.1.dist-info/LICENSE
mdsconnector-1.8.1.dist-info/METADATA
mdsconnector-1.8.1.dist-info/WHEEL
mdsconnector-1.8.1.dist-info/top_level.txt
mdsconnector-1.8.1.dist-info/RECORD
