Metadata-Version: 2.1
Name: mdsconnector
Version: 1.8.1
Summary: Remote call to MDSplus objects
Author: MDSplus Core Development Team
Author-email: mdsplus_dev@psfc.mit.edu
License: MIT License
Project-URL: Homepage, https://github.com/MDSplus/mdsConnector
Keywords: MDSplus,Data Managment,Data Acquisition,Magnetic Fusion Energy,Remote Data Access
Classifier: License :: OSI Approved :: MIT License
Classifier: Programming Language :: Python
Classifier: Programming Language :: Python :: 3
Classifier: Development Status :: 3 - Alpha
Classifier: Intended Audience :: Developers
Classifier: Intended Audience :: System Administrators
Classifier: Intended Audience :: Science/Research
Classifier: Operating System :: OS Independent
Classifier: Topic :: Internet
Classifier: Topic :: Software Development :: Libraries :: Python Modules
Classifier: Topic :: Software Development :: Object Brokering
Classifier: Topic :: System :: Clustering
Classifier: Topic :: System :: Distributed Computing
Classifier: Topic :: System :: Monitoring
Classifier: Topic :: System :: Networking
Classifier: Topic :: System :: Systems Administration
Classifier: Topic :: Scientific/Engineering :: Physics
Requires-Python: >2.5
License-File: LICENSE
Requires-Dist: rpyc ==4.1.5
Requires-Dist: dill <=0.3.2
Requires-Dist: plumbum <=1.6.9
Requires-Dist: numpy
Provides-Extra: test
Requires-Dist: mypy ; extra == 'test'
Requires-Dist: black ; extra == 'test'
Requires-Dist: isort ; extra == 'test'
Requires-Dist: flake8 ; extra == 'test'
Requires-Dist: bumpver ; extra == 'test'
Requires-Dist: pip-tools ; extra == 'test'
Requires-Dist: pytest ; extra == 'test'
